BioSTEAMconnectors/DayCent_RUNME.py
BioSTEAMconnectors/__init__.py
BioSTEAMconnectors/DayCent/FD-CIC_2021_dynamic.xlsm
BioSTEAMconnectors/DayCent/README.md
BioSTEAMconnectors/DayCent/__init__.py
BioSTEAMconnectors/DayCent/_daycent.py
BioSTEAMconnectors/DayCent/_fdcic.py
BioSTEAMconnectors/DayCent/user_data.xlsx
biosteamconnectors-0.0.3.dist-info/LICENSE.txt
biosteamconnectors-0.0.3.dist-info/METADATA
biosteamconnectors-0.0.3.dist-info/WHEEL
biosteamconnectors-0.0.3.dist-info/top_level.txt
biosteamconnectors-0.0.3.dist-info/RECORD
