Metadata-Version: 2.1
Name: biosteamconnectors
Version: 0.0.3
Summary: Automates DayCent and FDCIC calculator to find feedstock emissions
Home-page: https://github.com/emilypl2/BioSTEAMconnectors
Author: Emily Lin
Author-email: Emilypl2@illinois.edu
License: UIUC
Project-URL: Guest Group Lab, https://engineeringforsustainability.com/
Project-URL: CABBI-DayCent, https://github.com/cabbi-bio/DayCent-CABBI
Keywords: techno-economic analysis,life cycle assessment
Platform: Windows
Platform: Linux
Classifier: License :: OSI Approved :: University of Illinois/NCSA Open Source License
Classifier: Environment :: Console
Classifier: Topic :: Education
Classifier: Topic :: Scientific/Engineering
Classifier: Topic :: Scientific/Engineering :: Chemistry
Classifier: Topic :: Scientific/Engineering :: Mathematics
Classifier: Intended Audience :: Developers
Classifier: Intended Audience :: Education
Classifier: Intended Audience :: Manufacturing
Classifier: Intended Audience :: Science/Research
Classifier: Natural Language :: English
Classifier: Operating System :: MacOS
Classifier: Operating System :: Microsoft :: Windows
Classifier: Operating System :: POSIX
Classifier: Operating System :: POSIX :: BSD
Classifier: Operating System :: POSIX :: Linux
Classifier: Operating System :: Unix
Classifier: Programming Language :: Python :: 3.7
Classifier: Programming Language :: Python :: 3.8
License-File: LICENSE.txt
Requires-Dist: biosteam (>=2.31.21)
Requires-Dist: thermosteam (>=0.27.18)
Requires-Dist: pandas (>=1.3.2)
Requires-Dist: numpy
Requires-Dist: xlwings
